{
	"_meta": {
		"sources": [
			"loopback/common/models",
			"loopback/server/models",
			"../common/models",
			"./models"
		],
		"mixins": [
			"loopback/common/mixins",
			"loopback/server/mixins",
			"../common/mixins",
			"./mixins"
		]
	},
	"User": {
		"dataSource": "db"
	},
	"AccessToken": {
		"dataSource": "db",
		"public": false
	},
	"ACL": {
		"dataSource": "db",
		"public": false
	},
	"RoleMapping": {
		"dataSource": "db",
		"public": false,
		"options": {
			"strictObjectIDCoercion": true
		}
	},
	"Role": {
		"dataSource": "db",
		"public": false
	},
	"AdPermission": {
		"dataSource": "sandbox_himanshu",
		"public": true
	},
	"Agents": {
		"dataSource": "sandbox_himanshu",
		"public": false
	},
	"AgentsAssignment": {
		"dataSource": "sandbox_himanshu",
		"public": false
	},
	"City": {
		"dataSource": "sandbox_himanshu",
		"public": false
	},
	"CityMunicipality": {
		"dataSource": "sandbox_himanshu",
		"public": false
	},
	"CommercialListings": {
		"dataSource": "sandbox_himanshu",
		"public": false
	},
	"CondoProfile": {
		"dataSource": "sandbox_himanshu",
		"public": false
	},
	"CondosCaCity": {
		"dataSource": "sandbox_himanshu",
		"public": false
	},
	"CondosCaMunicipality": {
		"dataSource": "sandbox_himanshu",
		"public": false
	},
	"CondosCaNeighbourhood": {
		"dataSource": "sandbox_himanshu",
		"public": false
	},
	"CondosCaNeighbourhoodWeb": {
		"dataSource": "sandbox_himanshu",
		"public": false
	},
	"DemographicAge": {
		"dataSource": "sandbox_himanshu",
		"public": false
	},
	"DemographicChildren": {
		"dataSource": "sandbox_himanshu",
		"public": false
	},
	"DemographicConstruction": {
		"dataSource": "sandbox_himanshu",
		"public": false
	},
	"DemographicEducation": {
		"dataSource": "sandbox_himanshu",
		"public": false
	},
	"DemographicEmployment": {
		"dataSource": "sandbox_himanshu",
		"public": false
	},
	"DemographicGender": {
		"dataSource": "sandbox_himanshu",
		"public": false
	},
	"DemographicGeneral": {
		"dataSource": "sandbox_himanshu",
		"public": false
	},
	"DemographicIncome": {
		"dataSource": "sandbox_himanshu",
		"public": false
	},
	"DemographicMaritalstatus": {
		"dataSource": "sandbox_himanshu",
		"public": false
	},
	"DemographicMothertongue": {
		"dataSource": "sandbox_himanshu",
		"public": false
	},
	"DemographicNeighbourhood": {
		"dataSource": "sandbox_himanshu",
		"public": false
	},
	"DemographicOwnership": {
		"dataSource": "sandbox_himanshu",
		"public": false
	},
	"DemographicReligion": {
		"dataSource": "sandbox_himanshu",
		"public": false
	},
	"DemographicWorklocation": {
		"dataSource": "sandbox_himanshu",
		"public": false
	},
	"DemographicWorktransportation": {
		"dataSource": "sandbox_himanshu",
		"public": false
	},
	"Demographics": {
		"dataSource": "sandbox_himanshu",
		"public": false
	},
	"Division": {
		"dataSource": "sandbox_himanshu",
		"public": false
	},
	"Favorites": {
		"dataSource": "sandbox_himanshu",
		"public": false
	},
	"Leads": {
		"dataSource": "sandbox_himanshu",
		"public": false
	},
	"LeadsNotes": {
		"dataSource": "sandbox_himanshu",
		"public": false
	},
	"LeadsType": {
		"dataSource": "sandbox_himanshu",
		"public": false
	},
	"Listings": {
		"dataSource": "sandbox_himanshu",
		"public": false
	},
	"ListingsType": {
		"dataSource": "sandbox_himanshu",
		"public": false
	},
	"Municipality": {
		"dataSource": "sandbox_himanshu",
		"public": false
	},
	"Neighbourhood": {
		"dataSource": "sandbox_himanshu",
		"public": false
	},
	"NeighbourhoodProfile": {
		"dataSource": "sandbox_himanshu",
		"public": false
	},
	"PriceRange": {
		"dataSource": "sandbox_himanshu",
		"public": false
	},
	"PropertyListings": {
		"dataSource": "sandbox_himanshu",
		"public": false
	},
	"PropertyType": {
		"dataSource": "sandbox_himanshu",
		"public": false
	},
	"Province": {
		"dataSource": "sandbox_himanshu",
		"public": false
	},
	"Schools": {
		"dataSource": "sandbox_himanshu",
		"public": false
	},
	"Stats": {
		"dataSource": "sandbox_himanshu",
		"public": false
	},
	"Template": {
		"dataSource": "sandbox_himanshu",
		"public": false
	},
	"TemplateCriteria": {
		"dataSource": "sandbox_himanshu",
		"public": false
	},
	"TemplateModule": {
		"dataSource": "sandbox_himanshu",
		"public": false
	},
	"TemplateType": {
		"dataSource": "sandbox_himanshu",
		"public": false
	},
	"UnlistedListings": {
		"dataSource": "sandbox_himanshu",
		"public": false
	},
	"UserHistory": {
		"dataSource": "sandbox_himanshu",
		"public": false
	},
	"UserHistoryType": {
		"dataSource": "sandbox_himanshu",
		"public": false
	},
	"Vertical": {
		"dataSource": "sandbox_himanshu",
		"public": false
	},
	"WpCommentmeta": {
		"dataSource": "sandbox_himanshu",
		"public": false
	},
	"WpComments": {
		"dataSource": "sandbox_himanshu",
		"public": false
	},
	"WpLinks": {
		"dataSource": "sandbox_himanshu",
		"public": false
	},
	"WpOptions": {
		"dataSource": "sandbox_himanshu",
		"public": false
	},
	"WpPostmeta": {
		"dataSource": "sandbox_himanshu",
		"public": false
	},
	"WpPosts": {
		"dataSource": "sandbox_himanshu",
		"public": false
	},
	"WpTermRelationships": {
		"dataSource": "sandbox_himanshu",
		"public": false
	},
	"WpTermTaxonomy": {
		"dataSource": "sandbox_himanshu",
		"public": false
	},
	"WpTermmeta": {
		"dataSource": "sandbox_himanshu",
		"public": false
	},
	"WpTerms": {
		"dataSource": "sandbox_himanshu",
		"public": false
	},
	"WpUsermeta": {
		"dataSource": "sandbox_himanshu",
		"public": false
	},
	"WpUsers": {
		"dataSource": "sandbox_himanshu",
		"public": false
	}
}